quimb/__init__.py
quimb/_version.py
quimb/calc.py
quimb/core.py
quimb/evo.py
quimb/gates.py
quimb/schematic.py
quimb/utils.py
quimb/utils_plot.py
quimb/experimental/__init__.py
quimb/experimental/autojittn.py
quimb/experimental/schematic.py
quimb/experimental/tn_marginals.py
quimb/experimental/belief_propagation/__init__.py
quimb/experimental/belief_propagation/hd1gbp.py
quimb/experimental/cluster_update/__init__.py
quimb/experimental/cluster_update/cluster_update_old.py
quimb/experimental/cluster_update/cxu.py
quimb/experimental/cluster_update/cxu_old.py
quimb/experimental/cluster_update/new FullUpdate2D.ipynb
quimb/experimental/merabuilder/__init__.py
quimb/experimental/merabuilder/merabuilder demo.ipynb
quimb/experimental/merabuilder/merabuilder.py
quimb/experimental/misc/__init__.py
quimb/experimental/misc/cp_decomp.py
quimb/experimental/misc/misc.py
quimb/experimental/misc/peps_dmrg.py
quimb/experimental/misc/renormalization.ipynb
quimb/experimental/misc/renormalization.py
quimb/experimental/misc/tn_virtual_tree_gauge.ipynb
quimb/experimental/misc/tn_virtual_tree_gauge.py
quimb/experimental/operatorbuilder/__init__.py
quimb/experimental/operatorbuilder/builder.py
quimb/experimental/operatorbuilder/configcore.py
quimb/experimental/operatorbuilder/hilbertspace.py
quimb/experimental/operatorbuilder/models.py
quimb/experimental/operatorbuilder/operatorbuilder demo.ipynb
quimb/experimental/operatorbuilder/pepobuilder.py
quimb/experimental/tensor_1d_gate/tensor_1d_mpo_gate_methods.py
quimb/experimental/tnvmc/__init__.py
quimb/experimental/tnvmc/tnvmc demo.ipynb
quimb/experimental/tnvmc/tnvmc.py
quimb/gen/__init__.py
quimb/gen/operators.py
quimb/gen/rand.py
quimb/gen/states.py
quimb/linalg/__init__.py
quimb/linalg/approx_spectral.py
quimb/linalg/autoblock.py
quimb/linalg/base_linalg.py
quimb/linalg/mpi_launcher.py
quimb/linalg/numpy_linalg.py
quimb/linalg/rand_linalg.py
quimb/linalg/scipy_linalg.py
quimb/linalg/slepc_linalg.py
quimb/tensor/__init__.py
quimb-1.11.2.dist-info/METADATA
quimb-1.11.2.dist-info/WHEEL
quimb-1.11.2.dist-info/licenses/LICENSE.txt
quimb-1.11.2.dist-info/RECORD
